whyslslib/__init__.py
whyslslib/libfuncs.py
whyslslib-0.1.dist-info/METADATA
whyslslib-0.1.dist-info/WHEEL
whyslslib-0.1.dist-info/top_level.txt
whyslslib-0.1.dist-info/RECORD
