Metadata-Version: 2.1
Name: whyslslib
Version: 0.1
Summary: sls test lib
Home-page: UNKNOWN
Author: why
Author-email: UNKNOWN
License: MIT
Platform: UNKNOWN
